boilerdaq/__init__.py
boilerdaq/daq.py
boilerdaq/dummy.py
boilerdaq/shim.py
boilerdaq/types.py
boilerdaq/models/__init__.py
boilerdaq/models/params.py
boilerdaq/models/paths.py
boilerdaq/stages/__init__.py
boilerdaq/stages/calibrate.py
boilerdaq/stages/run.py
boilerdaq/stages/test.py
boilerdaq/stages/controlled/__init__.py
boilerdaq/stages/controlled/benchmark.py
boilerdaq/stages/controlled/control.py
boilerdaq/stages/controlled/set_voltage.py
boilerdaq/stages/controlled/surface_control.py
boilerdaq-2024.1.2.dist-info/LICENSE
boilerdaq-2024.1.2.dist-info/WHEEL
boilerdaq-2024.1.2.dist-info/METADATA
boilerdaq-2024.1.2.dist-info/RECORD
