Metadata-Version: 2.1
Name: boilerdaq
Version: 2024.1.2
Summary: Data acquisition for a nucleate pool boiling experimental apparatus
Author-email: Blake Naccarato <blake.naccarato@gmail.com>
Requires-Python: >=3.11
Classifier: License :: OSI Approved :: MIT License
Classifier: Programming Language :: Python :: 3.11
Classifier: Programming Language :: Python :: 3.12
Requires-Dist: boilercore>=2024.1.3
Requires-Dist: libusb>=1.0.27
Requires-Dist: mcculw>=1.0.0
Requires-Dist: pandas[hdf5,performance]>=2.2.0
Requires-Dist: pydantic>=2.6.1
Requires-Dist: pyqtgraph>=0.13.3
Requires-Dist: pyvisa>=1.14.1
Requires-Dist: pyusb>=1.2.1
Requires-Dist: pyvisa-py>=0.7.2
Requires-Dist: simple-pid>=2.0.0
Requires-Dist: pyvisa-sim>=0.6.0
Requires-Dist: uldaq>=1.2.3
Requires-Dist: zeroconf>=0.132.2
Project-URL: Changes, https://softboiler.github.io/boilerdaq/changelog.html
Project-URL: Docs, https://softboiler.github.io/boilerdaq
Project-URL: Home, https://github.com/softboiler/boilerdaq
Project-URL: Tracker, https://github.com/softboiler/boilerdaq/issues
